fl_api_requester/FLAPIConnectionData.py
fl_api_requester/FLAPIRequester.py
fl_api_requester/__init__.py
fl_api_requester/dto/DTO.py
fl_api_requester/dto/request/alliance/CreateAllianceDTO.py
fl_api_requester/dto/request/alliance/RemoveAllianceDTO.py
fl_api_requester/dto/request/authentication/AuthenticationRequestDTO.py
fl_api_requester/dto/request/discord/AddAllianceToDiscordDTO.py
fl_api_requester/dto/request/discord/AddChannelsToDiscordDTO.py
fl_api_requester/dto/request/discord/CreateDiscordDTO.py
fl_api_requester/dto/request/discord/RemoveChannelsFromDiscordDTO.py
fl_api_requester/dto/request/discord/RemoveDiscordDTO.py
fl_api_requester/dto/request/discord_channel/DiscordChannelRequestDTO.py
fl_api_requester/dto/request/planet/AddPlanetDTO.py
fl_api_requester/dto/request/planet/RemovePlanetDTO.py
fl_api_requester/dto/request/planet/RemoveSpecificPlanetDTO.py
fl_api_requester/dto/request/player/CreatePlayerDTO.py
fl_api_requester/dto/request/player/RemovePlayerDTO.py
fl_api_requester/dto/request/player/SetAllianceDTO.py
fl_api_requester/dto/request/player/SetPlayerRolesDTO.py
fl_api_requester/dto/request/war/SetRespawnTimerDTO.py
fl_api_requester/dto/request/war/StartWarDTO.py
fl_api_requester/dto/request/war/StopWarDTO.py
fl_api_requester/dto/request/war/WarAttackRequestDTO.py
fl_api_requester/dto/response/alliance/AllianceDTO.py
fl_api_requester/dto/response/alliance/AllianceNameDTO.py
fl_api_requester/dto/response/authentication/AuthenticationResponseDTO.py
fl_api_requester/dto/response/discord/DiscordDTO.py
fl_api_requester/dto/response/discord_channel/DiscordChannelResponseDTO.py
fl_api_requester/dto/response/planet/PlanetDTO.py
fl_api_requester/dto/response/planet/PlanetOwnerDTO.py
fl_api_requester/dto/response/player/PlayerDTO.py
fl_api_requester/dto/response/war/WarAttackResponseDTO.py
fl_api_requester/dto/response/war/WarDTO.py
fl_api_requester/exception/APIErrorException.py
fl_api_requester-1.0.11.dist-info/LICENSE
fl_api_requester-1.0.11.dist-info/METADATA
fl_api_requester-1.0.11.dist-info/WHEEL
fl_api_requester-1.0.11.dist-info/top_level.txt
fl_api_requester-1.0.11.dist-info/RECORD
